graph_sitter/__init__.py
graph_sitter/_proxy.py
graph_sitter/codemod.py
graph_sitter/enums.py
graph_sitter/exceptions.py
graph_sitter/py.typed
graph_sitter/secrets.py
graph_sitter/topological_sort.py
graph_sitter/tree_sitter_parser.py
graph_sitter/types.py
graph_sitter/utils.py
graph_sitter/writer_decorators.py
graph_sitter/ai/converters.py
graph_sitter/ai/helpers.py
graph_sitter/code_generation/__init__.py
graph_sitter/code_generation/current_code_codebase.py
graph_sitter/code_generation/enums.py
graph_sitter/code_generation/graph_sitter_codebase.py
graph_sitter/code_generation/mdx_docs_generation.py
graph_sitter/code_generation/doc_utils/__init__.py
graph_sitter/code_generation/doc_utils/canonicals.py
graph_sitter/code_generation/doc_utils/skills.py
graph_sitter/code_generation/doc_utils/utils.py
graph_sitter/code_generation/prompts/__init__.py
graph_sitter/code_generation/prompts/api_docs.py
graph_sitter/codebase/__init__.py
graph_sitter/codebase/codebase_ai.py
graph_sitter/codebase/codebase_analysis.py
graph_sitter/codebase/codebase_graph.py
graph_sitter/codebase/config.py
graph_sitter/codebase/config_parser.py
graph_sitter/codebase/control_flow.py
graph_sitter/codebase/diff_lite.py
graph_sitter/codebase/multigraph.py
graph_sitter/codebase/range_index.py
graph_sitter/codebase/resolution_stack.py
graph_sitter/codebase/span.py
graph_sitter/codebase/transaction_manager.py
graph_sitter/codebase/transactions.py
graph_sitter/codebase/validation.py
graph_sitter/codebase/factory/codebase_factory.py
graph_sitter/codebase/factory/get_session.ipynb
graph_sitter/codebase/factory/get_session.py
graph_sitter/codebase/flagging/code_flag.py
graph_sitter/codebase/flagging/enums.py
graph_sitter/codebase/flagging/flags.py
graph_sitter/codebase/node_classes/__init__.py
graph_sitter/codebase/node_classes/node_classes.py
graph_sitter/codebase/node_classes/py_node_classes.py
graph_sitter/codebase/node_classes/ts_node_classes.py
graph_sitter-7.0.1.dist-info/METADATA
graph_sitter-7.0.1.dist-info/WHEEL
graph_sitter-7.0.1.dist-info/entry_points.txt
graph_sitter-7.0.1.dist-info/RECORD
graph_sitter-7.0.1.dist-info/licenses/LICENSE
