Metadata-Version: 2.4
Name: graph-sitter
Version: 7.0.1
Summary: Add your description here
License: 
License-File: LICENSE
Classifier: Development Status :: 4 - Beta
Classifier: Environment :: MacOS X
Classifier: Intended Audience :: Developers
Classifier: License :: OSI Approved :: Apache Software License
Classifier: Programming Language :: Python
Classifier: Programming Language :: Python :: 3
Classifier: Programming Language :: Python :: 3.12
Classifier: Programming Language :: Python :: 3.13
Classifier: Topic :: Software Development
Requires-Python: <3.14,>=3.12
Requires-Dist: anthropic==0.23.1
Requires-Dist: astor<1.0.0,>=0.8.1
Requires-Dist: autoflake>=2.3.1
Requires-Dist: backoff==2.2.1
Requires-Dist: black>=24.8.0
Requires-Dist: click>=8.1.7
Requires-Dist: codegen-git
Requires-Dist: codeowners<1.0.0,>=0.6.0
Requires-Dist: dataclasses-json<1.0.0,>=0.6.4
Requires-Dist: dicttoxml<2.0.0,>=1.7.16
Requires-Dist: docstring-parser<1.0,>=0.16
Requires-Dist: emoji>=2.14.0
Requires-Dist: hatch-vcs>=0.4.0
Requires-Dist: hatchling>=1.25.0
Requires-Dist: humanize<5.0.0,>=4.10.0
Requires-Dist: inflection<1.0.0,>=0.5.1
Requires-Dist: isort>=5.13.2
Requires-Dist: jsbeautifier<2.0.0,>=1.15.1
Requires-Dist: lazy-object-proxy>=0.0.0
Requires-Dist: loguru<1.0.0,>=0.7.2
Requires-Dist: mini-racer>=0.12.4
Requires-Dist: networkx>=3.4.1
Requires-Dist: openai==1.59.9
Requires-Dist: pip>=24.3.1
Requires-Dist: plotly<6.0.0,>=5.24.0
Requires-Dist: pydantic-core>=2.23.4
Requires-Dist: pydantic<3.0.0,>=2.9.2
Requires-Dist: pyinstrument>=5.0.0
Requires-Dist: pyjson5==1.6.8
Requires-Dist: pyright<2.0.0,>=1.1.372
Requires-Dist: pytest-snapshot>=0.9.0
Requires-Dist: python-levenshtein<1.0.0,>=0.25.1
Requires-Dist: requests>=2.32.3
Requires-Dist: rich<14.0.0,>=13.7.1
Requires-Dist: rustworkx>=0.15.1
Requires-Dist: sentry-sdk==2.20.0
Requires-Dist: tabulate<1.0.0,>=0.9.0
Requires-Dist: tenacity>=9.0.0
Requires-Dist: termcolor>=2.4.0
Requires-Dist: tiktoken<1.0.0,>=0.5.1
Requires-Dist: tree-sitter-javascript>=0.23.1
Requires-Dist: tree-sitter-python>=0.23.4
Requires-Dist: tree-sitter-typescript>=0.23.2
Requires-Dist: tree-sitter>=0.23.1
Requires-Dist: typing-extensions>=4.12.2
Requires-Dist: watchfiles<1.1.0,>=1.0.0
Requires-Dist: wrapt<2.0.0,>=1.16.0
Requires-Dist: xmltodict<1.0.0,>=0.13.0
Provides-Extra: types
Requires-Dist: types-networkx>=3.2.1.20240918; extra == 'types'
Requires-Dist: types-tabulate>=0.9.0.20240106; extra == 'types'
